codarcane/__init__.py
codarcane/snippet_manager.py
codarcane-0.0.3.dist-info/LICENSE.txt
codarcane-0.0.3.dist-info/METADATA
codarcane-0.0.3.dist-info/WHEEL
codarcane-0.0.3.dist-info/entry_points.txt
codarcane-0.0.3.dist-info/top_level.txt
codarcane-0.0.3.dist-info/RECORD
