Metadata-Version: 2.1
Name: codarcane
Version: 0.0.3
Summary: Your go-to repository for code snippets
Home-page: https://gitlab.com/rochdikhalid/codarcane
Author: Rochdi Khalid
Project-URL: Bug Tracker, https://gitlab.com/rochdikhalid/codarcane/-/issues
Project-URL: repository, https://gitlab.com/rochdikhalid/codarcane
Classifier: Programming Language :: Python :: 3
Classifier: License :: OSI Approved :: MIT License
Classifier: Operating System :: OS Independent
Requires-Python: >=3.6
License-File: LICENSE.txt
Requires-Dist: click
Requires-Dist: pyperclip
